wf_core_data_dashboard/__init__.py
wf_core_data_dashboard/__main__.py
wf_core_data_dashboard/app.py
wf_core_data_dashboard/core.py
wf_core_data_dashboard/assessments/__init__.py
wf_core_data_dashboard/assessments/fastbridge.py
wf_core_data_dashboard/assessments/mefs.py
wf_core_data_dashboard/assessments/nwea.py
wf_core_data_dashboard/routes/__init__.py
wf_core_data_dashboard-0.7.0.dist-info/LICENSE
wf_core_data_dashboard-0.7.0.dist-info/METADATA
wf_core_data_dashboard-0.7.0.dist-info/WHEEL
wf_core_data_dashboard-0.7.0.dist-info/top_level.txt
wf_core_data_dashboard-0.7.0.dist-info/RECORD
