Metadata-Version: 2.1
Name: wf-core-data-dashboard
Version: 0.7.0
Summary: Dashboard for viewing Wildflower data
Home-page: https://github.com/WildflowerSchools/wf-core-data-dashboard
Author: Theodore Quinn
Author-email: ted.quinn@wildflowerschools.org
License: UNKNOWN
Keywords: dashboard
Platform: UNKNOWN
Classifier: Intended Audience :: Developers
Classifier: License :: OSI Approved :: MIT License
Classifier: Operating System :: OS Independent
Classifier: Programming Language :: Python
Requires-Dist: fastapi[all]
Requires-Dist: pandas (>=1.3)
Requires-Dist: wf-core-data-python (>=1.3.0)
Requires-Dist: wf-fastbridge-utils (>=1.2.0)
Requires-Dist: wf-mefs-utils (>=1.2.0)
Requires-Dist: wf-nwea-utils (>=1.2.0)
